bokehheat/__init__.py
bokehheat/_version.py
bokehheat/error.json
bokehheat/heat.py
bokehheat/jheat.py
bokehheat-0.0.7.dist-info/LICENSE.txt
bokehheat-0.0.7.dist-info/METADATA
bokehheat-0.0.7.dist-info/WHEEL
bokehheat-0.0.7.dist-info/top_level.txt
bokehheat-0.0.7.dist-info/RECORD
