Metadata-Version: 2.1
Name: bokehheat
Version: 0.0.7
Summary: A python3 bokeh based boolean data, categorical data, numerical data, dendrogram, and heatmap plotting library.
Home-page: https://gitlab.com/biotransistor/bokehheat
Author: Elmar Bucher
Author-email: ulmusfagus@tutanota.de
License: GPL>=3
Project-URL: Bug Reports, https://gitlab.com/biotransistor/bokehheat/issues
Project-URL: Funding, https://donate.doctorswithoutborders.org
Project-URL: Source, https://gitlab.com/biotransistor/bokehheat/
Keywords: visualization bokeh dendrogram cladogram heatmap
Classifier: Development Status :: 4 - Beta
Classifier: Intended Audience :: Developers
Classifier: Intended Audience :: Science/Research
Classifier: Topic :: Multimedia :: Graphics
Classifier: Topic :: Scientific/Engineering :: Bio-Informatics
Classifier: Topic :: Scientific/Engineering :: Visualization
Classifier: License :: OSI Approved :: GNU General Public License v3 or later (GPLv3+)
Classifier: Programming Language :: Python :: 3.6
Requires-Python: >=3.6
License-File: LICENSE.txt
Requires-Dist: bokeh
Requires-Dist: matplotlib
Requires-Dist: pandas
Requires-Dist: scipy
Requires-Dist: selenium
